{
  "title": {
    "home": "Home",
    "pong": "Pong",
    "c4": "Connect 4",
    "profile": "Profile",
    "friends": "Friends",
    "settings": "Settings",
    "login": "Login",
    "logout": "Logout",
    "local": "Local",
    "lobby": "Lobby",
    "matchmaking": "Matchmaking",
    "remote": "Remote",
    "tournament": "Tournament",
    "ranking": "Ranking",
    "notif": "Notifications",
    "createUser": "Create User",
    "createProfile": "Create new Profile",
    "mode": "Mode"
  },
  "button": {
    "close": "Close",
    "accept": "Accept",
    "refuse": "Refuse",
    "invite": "Invite",
    "save": "Save",
    "cancel": "Cancel",
    "return": "Return",
    "stop": "Stop",
    "help": "Help",
    "giveUp": "Give up",
    "show": "Show",
    "change": "Change",
    "chooseFile": "Choose a File",
    "upload": "Upload",
    "set": "Set",
    "handle": "Handle",
    "data": "Data",
    "send": "Send",
    "delete": "Delete",
    "all": "all",
    "join": "Join",
    "addFriend": "Add Friend",
    "remove": "Remove"
  },
  "user": {
    "you": "You",
    "is": "is",
    "your": "Your",
    "account": "Account",
    "avatar": "Avatar",
    "maiden": "MaidenLess",
    "current": "Current",
    "pleaseFriend": "Please add Friends",
    "choose": "Choose your Avatar",
    "orUpload": "Or Upload your own",
    "selectAvatar": "Select or Upload your profile Avatar"
  },
  "game": {
    "label": "Game",
    "win": "Win",
    "wins": "Wins",
    "won": "Won",
    "loss": "Loss",
    "lost": "Lost",
    "play": "Play",
    "next": "Next",
    "time": "Time Left",
    "its": "It's",
    "turn": "Turn",
    "match": "Match",
    "found": "Found",
    "loadling": "Loading",
    "inviteMatch": "Invite to a Match",
    "noInvite": "No Invites",
    "player": "Player",
    "blue": "Blue",
    "red": "Red",
    "selectNbPlayer": "Select number of players",
    "paused": "is paused",
    "start": "Start",
    "battle": "Battle",
    "waiting": "waiting for",
    "history": "History",
    "winRate": "Win Rate",
    "n/a": "n/a"
  },
  "homePage": {
    "title": "Welcome to Our Pong!",
    "descriptionHomeMessage": "Explore the depth of the Pong game, play with friends, and personalize your profile as you desire!",
    "descriptionHomeMessage2": "✨ Have fun! ✨"
  },
  "input": {
    "label": {
      "username": "Username",
      "password": "Password",
      "email": "E-mail",
      "confirm": "Confirm",
      "3to10": "3 to 10",
      "language": "Language",
      "old": "Old",
      "new": "New"
    },
    "error": {
      "empty": "is empty",
      "short": "is too short",
      "weak": "is too weak",
      "invalidChar": "contains invalid characters",
      "match": "does not match",
      "unique": "is already taken",
      "valid": "is not a valid",
      "incorrect": "Incorrect"
    },
    "preview": {
      "opponent": "Enter opponent's username",
      "username": "Enter Username",
      "noFile": "No File chosen",
      "old": "old",
      "new": "new",
      "email": "-email@google.com"
    }
  },
  "modal": {
    "title": {
      "error": "Error",
      "success": "Success",
      "congrats": "Congratulations",
      "inviteMatch": "Invite to a Match",
      "inviteGames": "Games Invites",
      "invite": "Invites",
      "auth": "Authentification",
      "accountCreation": "Account Creation"
    },
    "message": {
      "over": "is over",
      "clickNewTourn": "click here if you want to start another tournament",
      "bye": "Goodbye",
      "welcome": "Welcome",
      "notLog": "You're not authentified, please login to access this page",
      "failConnectServer": "Unable to connect to the server, please try again later",
      "serverLoading": "The server has restarted and need some time to finish initialization, please wait a little and retry",
      "authError": "Authentification error, please re-login",
      "successChange": "was changed successfully",
      "successDeleteAccount": "Your account was successfully deleted, all associated data is being anonymized",
      "alreadyLog": "You are already logged in",
      "accountCreation": "Your new account was successfully created!",
      "failTournament": "Failed to retrieve tournament information",
      "wonTournament": "won the tournament",
      "help": "Space to start the game.<br>Space to pause/unpause the game.<br>W to go up.<br>S to go down.<br>In local game for the Red Player:<br> -ArrowUp to go up.<br> -ArrowDown to go down.",
      "lostGame": "Better luck next time",
      "addYourself": "You can't add yourself as a friend",
      "inviteYou": "invites you to a game of"
    }
  }
}
